{
    "subjects": [{
        "rate": "9.0",
        "cover_x": 6611,
        "title": "心灵奇旅",
        "url": "https:\/\/movie.douban.com\/subject\/24733428\/",
        "playable": false,
        "cover": "https://img9.doubanio.com\/view\/photo\/s_ratio_poster\/public\/p2626308994.jpg",
        "id": "24733428",
        "cover_y": 9435,
        "is_new": true
    }, {
        "rate": "6.4",
        "cover_x": 2764,
        "title": "神奇女侠1984",
        "url": "https:\/\/movie.douban.com\/subject\/27073752\/",
        "playable": false,
        "cover": "https://img1.doubanio.com\/view\/photo\/s_ratio_poster\/public\/p2626959989.jpg",
        "id": "27073752",
        "cover_y": 4096,
        "is_new": false
    }, {
        "rate": "6.7",
        "cover_x": 507,
        "title": "敢梦有爱",
        "url": "https:\/\/movie.douban.com\/subject\/27153409\/",
        "playable": false,
        "cover": "https://img2.doubanio.com\/view\/photo\/s_ratio_poster\/public\/p2587589753.jpg",
        "id": "27153409",
        "cover_y": 750,
        "is_new": true
    }, {
        "rate": "7.4",
        "cover_x": 630,
        "title": "圣诞速配",
        "url": "https:\/\/movie.douban.com\/subject\/35264411\/",
        "playable": false,
        "cover": "https://img9.doubanio.com\/view\/photo\/s_ratio_poster\/public\/p2628196596.jpg",
        "id": "35264411",
        "cover_y": 1200,
        "is_new": true
    }, {
        "rate": "6.2",
        "cover_x": 558,
        "title": "拯救圣诞记2",
        "url": "https:\/\/movie.douban.com\/subject\/34909171\/",
        "playable": false,
        "cover": "https://img9.doubanio.com\/view\/photo\/s_ratio_poster\/public\/p2623323526.jpg",
        "id": "34909171",
        "cover_y": 830,
        "is_new": true
    }, {
        "rate": "7.1",
        "cover_x": 1000,
        "title": "刻在你心底的名字",
        "url": "https:\/\/movie.douban.com\/subject\/33408026\/",
        "playable": false,
        "cover": "https://img2.doubanio.com\/view\/photo\/s_ratio_poster\/public\/p2617820253.jpg",
        "id": "33408026",
        "cover_y": 1428,
        "is_new": false
    }, {
        "rate": "6.4",
        "cover_x": 4000,
        "title": "沐浴之王",
        "url": "https:\/\/movie.douban.com\/subject\/34894753\/",
        "playable": true,
        "cover": "https://img2.doubanio.com\/view\/photo\/s_ratio_poster\/public\/p2627788612.jpg",
        "id": "34894753",
        "cover_y": 5600,
        "is_new": false
    }, {
        "rate": "7.3",
        "cover_x": 1500,
        "title": "2020去死",
        "url": "https:\/\/movie.douban.com\/subject\/35275115\/",
        "playable": false,
        "cover": "https://img9.doubanio.com\/view\/photo\/s_ratio_poster\/public\/p2628834126.jpg",
        "id": "35275115",
        "cover_y": 2222,
        "is_new": true
    }, {
        "rate": "8.1",
        "cover_x": 1080,
        "title": "疯狂原始人2",
        "url": "https:\/\/movie.douban.com\/subject\/24298954\/",
        "playable": false,
        "cover": "https://img9.doubanio.com\/view\/photo\/s_ratio_poster\/public\/p2624607255.jpg",
        "id": "24298954",
        "cover_y": 1600,
        "is_new": false
    }, {
        "rate": "7.8",
        "cover_x": 2805,
        "title": "一秒钟",
        "url": "https:\/\/movie.douban.com\/subject\/30257787\/",
        "playable": true,
        "cover": "https://img1.doubanio.com\/view\/photo\/s_ratio_poster\/public\/p2628373757.jpg",
        "id": "30257787",
        "cover_y": 4134,
        "is_new": false
    }, {
        "rate": "7.5",
        "cover_x": 680,
        "title": "行骗天下JP：公主篇",
        "url": "https:\/\/movie.douban.com\/subject\/33476040\/",
        "playable": false,
        "cover": "https://img1.doubanio.com\/view\/photo\/s_ratio_poster\/public\/p2610002857.jpg",
        "id": "33476040",
        "cover_y": 962,
        "is_new": false
    }, {
        "rate": "7.3",
        "cover_x": 4000,
        "title": "夺冠",
        "url": "https:\/\/movie.douban.com\/subject\/30128916\/",
        "playable": true,
        "cover": "https://img2.doubanio.com\/view\/photo\/s_ratio_poster\/public\/p2620083313.jpg",
        "id": "30128916",
        "cover_y": 5587,
        "is_new": false
    }, {
        "rate": "7.6",
        "cover_x": 1500,
        "title": "电话",
        "url": "https:\/\/movie.douban.com\/subject\/30346025\/",
        "playable": false,
        "cover": "https://img1.doubanio.com\/view\/photo\/s_ratio_poster\/public\/p2625879789.jpg",
        "id": "30346025",
        "cover_y": 2172,
        "is_new": false
    }, {
        "rate": "7.7",
        "cover_x": 2160,
        "title": "信条",
        "url": "https:\/\/movie.douban.com\/subject\/30444960\/",
        "playable": true,
        "cover": "https://img9.doubanio.com\/view\/photo\/s_ratio_poster\/public\/p2618403186.jpg",
        "id": "30444960",
        "cover_y": 3201,
        "is_new": false
    }, {
        "rate": "7.5",
        "cover_x": 613,
        "title": "酒精计划",
        "url": "https:\/\/movie.douban.com\/subject\/30323120\/",
        "playable": false,
        "cover": "https://img3.doubanio.com\/view\/photo\/s_ratio_poster\/public\/p2628440350.jpg",
        "id": "30323120",
        "cover_y": 896,
        "is_new": false
    }, {
        "rate": "7.1",
        "cover_x": 700,
        "title": "消失的情人节",
        "url": "https:\/\/movie.douban.com\/subject\/35154957\/",
        "playable": false,
        "cover": "https://img3.doubanio.com\/view\/photo\/s_ratio_poster\/public\/p2618456760.jpg",
        "id": "35154957",
        "cover_y": 1014,
        "is_new": false
    }, {
        "rate": "7.3",
        "cover_x": 5906,
        "title": "我和我的家乡",
        "url": "https:\/\/movie.douban.com\/subject\/35051512\/",
        "playable": true,
        "cover": "https://img2.doubanio.com\/view\/photo\/s_ratio_poster\/public\/p2620453443.jpg",
        "id": "35051512",
        "cover_y": 8268,
        "is_new": false
    }, {
        "rate": "8.6",
        "cover_x": 1334,
        "title": "无依之地",
        "url": "https:\/\/movie.douban.com\/subject\/30458949\/",
        "playable": false,
        "cover": "https://img1.doubanio.com\/view\/photo\/s_ratio_poster\/public\/p2628328069.jpg",
        "id": "30458949",
        "cover_y": 2000,
        "is_new": false
    }, {
        "rate": "8.4",
        "cover_x": 1449,
        "title": "鬼灭之刃 剧场版 无限列车篇",
        "url": "https:\/\/movie.douban.com\/subject\/34845781\/",
        "playable": false,
        "cover": "https://img3.doubanio.com\/view\/photo\/s_ratio_poster\/public\/p2595123270.jpg",
        "id": "34845781",
        "cover_y": 2048,
        "is_new": false
    }, {
        "rate": "7.1",
        "cover_x": 2017,
        "title": "菊石",
        "url": "https:\/\/movie.douban.com\/subject\/30403683\/",
        "playable": false,
        "cover": "https://img2.doubanio.com\/view\/photo\/s_ratio_poster\/public\/p2618286922.jpg",
        "id": "30403683",
        "cover_y": 2992,
        "is_new": false
    }, {
        "rate": "8.0",
        "cover_x": 8100,
        "title": "玫瑰岛的不可思议的历史",
        "url": "https:\/\/movie.douban.com\/subject\/34982759\/",
        "playable": false,
        "cover": "https://img9.doubanio.com\/view\/photo\/s_ratio_poster\/public\/p2624341545.jpg",
        "id": "34982759",
        "cover_y": 12000,
        "is_new": false
    }, {
        "rate": "6.5",
        "cover_x": 2362,
        "title": "金刚川",
        "url": "https:\/\/movie.douban.com\/subject\/35155748\/",
        "playable": true,
        "cover": "https://img1.doubanio.com\/view\/photo\/s_ratio_poster\/public\/p2623301908.jpg",
        "id": "35155748",
        "cover_y": 3307,
        "is_new": false
    }, {
        "rate": "7.6",
        "cover_x": 2000,
        "title": "八佰",
        "url": "https:\/\/movie.douban.com\/subject\/26754233\/",
        "playable": true,
        "cover": "https://img9.doubanio.com\/view\/photo\/s_ratio_poster\/public\/p2615992304.jpg",
        "id": "26754233",
        "cover_y": 2800,
        "is_new": false
    }, {
        "rate": "6.3",
        "cover_x": 1000,
        "title": "风平浪静",
        "url": "https:\/\/movie.douban.com\/subject\/27589933\/",
        "playable": true,
        "cover": "https://img2.doubanio.com\/view\/photo\/s_ratio_poster\/public\/p2626255103.jpg",
        "id": "27589933",
        "cover_y": 1400,
        "is_new": false
    }, {
        "rate": "8.6",
        "cover_x": 1500,
        "title": "芝加哥七君子审判",
        "url": "https:\/\/movie.douban.com\/subject\/2609258\/",
        "playable": false,
        "cover": "https://img3.doubanio.com\/view\/photo\/s_ratio_poster\/public\/p2620161520.jpg",
        "id": "2609258",
        "cover_y": 2222,
        "is_new": false
    }, {
        "rate": "8.0",
        "cover_x": 2000,
        "title": "狼行者",
        "url": "https:\/\/movie.douban.com\/subject\/26694926\/",
        "playable": false,
        "cover": "https://img3.doubanio.com\/view\/photo\/s_ratio_poster\/public\/p2622396801.jpg",
        "id": "26694926",
        "cover_y": 3000,
        "is_new": false
    }, {
        "rate": "6.1",
        "cover_x": 1365,
        "title": "砍人快乐",
        "url": "https:\/\/movie.douban.com\/subject\/34954336\/",
        "playable": false,
        "cover": "https://img1.doubanio.com\/view\/photo\/s_ratio_poster\/public\/p2627618398.jpg",
        "id": "34954336",
        "cover_y": 2048,
        "is_new": false
    }, {
        "rate": "7.5",
        "cover_x": 1000,
        "title": "哆啦A梦：大雄的新恐龙",
        "url": "https:\/\/movie.douban.com\/subject\/34454004\/",
        "playable": false,
        "cover": "https://img9.doubanio.com\/view\/photo\/s_ratio_poster\/public\/p2624375776.jpg",
        "id": "34454004",
        "cover_y": 1412,
        "is_new": false
    }, {
        "rate": "6.7",
        "cover_x": 1080,
        "title": "陈翔六点半之民间高手",
        "url": "https:\/\/movie.douban.com\/subject\/35207868\/",
        "playable": true,
        "cover": "https://img3.doubanio.com\/view\/photo\/s_ratio_poster\/public\/p2629465650.jpg",
        "id": "35207868",
        "cover_y": 1920,
        "is_new": true
    }, {
        "rate": "7.7",
        "cover_x": 2233,
        "title": "1\/2的魔法",
        "url": "https:\/\/movie.douban.com\/subject\/30401849\/",
        "playable": true,
        "cover": "https://img2.doubanio.com\/view\/photo\/s_ratio_poster\/public\/p2616349563.jpg",
        "id": "30401849",
        "cover_y": 3190,
        "is_new": false
    }, {
        "rate": "6.8",
        "cover_x": 3000,
        "title": "姜子牙",
        "url": "https:\/\/movie.douban.com\/subject\/25907124\/",
        "playable": true,
        "cover": "https://img1.doubanio.com\/view\/photo\/s_ratio_poster\/public\/p2621219978.jpg",
        "id": "25907124",
        "cover_y": 4367,
        "is_new": false
    }, {
        "rate": "7.4",
        "cover_x": 1500,
        "title": "曼克",
        "url": "https:\/\/movie.douban.com\/subject\/34461705\/",
        "playable": false,
        "cover": "https://img9.doubanio.com\/view\/photo\/s_ratio_poster\/public\/p2623412955.jpg",
        "id": "34461705",
        "cover_y": 2222,
        "is_new": false
    }, {
        "rate": "5.7",
        "cover_x": 1500,
        "title": "午夜天空",
        "url": "https:\/\/movie.douban.com\/subject\/34442667\/",
        "playable": false,
        "cover": "https://img2.doubanio.com\/view\/photo\/s_ratio_poster\/public\/p2627465353.jpg",
        "id": "34442667",
        "cover_y": 2222,
        "is_new": true
    }, {
        "rate": "7.3",
        "cover_x": 640,
        "title": "无声",
        "url": "https:\/\/movie.douban.com\/subject\/33591810\/",
        "playable": false,
        "cover": "https://img1.doubanio.com\/view\/photo\/s_ratio_poster\/public\/p2621016058.jpg",
        "id": "33591810",
        "cover_y": 915,
        "is_new": false
    }, {
        "rate": "7.1",
        "cover_x": 1080,
        "title": "最幸福的季节",
        "url": "https:\/\/movie.douban.com\/subject\/30389671\/",
        "playable": false,
        "cover": "https://img3.doubanio.com\/view\/photo\/s_ratio_poster\/public\/p2625245511.jpg",
        "id": "30389671",
        "cover_y": 1600,
        "is_new": false
    }, {
        "rate": "7.2",
        "cover_x": 658,
        "title": "逃走的女人",
        "url": "https:\/\/movie.douban.com\/subject\/34958725\/",
        "playable": false,
        "cover": "https://img9.doubanio.com\/view\/photo\/s_ratio_poster\/public\/p2615399825.jpg",
        "id": "34958725",
        "cover_y": 937,
        "is_new": false
    }, {
        "rate": "6.8",
        "cover_x": 640,
        "title": "恋途未卜",
        "url": "https:\/\/movie.douban.com\/subject\/33371681\/",
        "playable": false,
        "cover": "https://img3.doubanio.com\/view\/photo\/s_ratio_poster\/public\/p2610762490.jpg",
        "id": "33371681",
        "cover_y": 906,
        "is_new": true
    }, {
        "rate": "8.1",
        "cover_x": 950,
        "title": "南山的部长们",
        "url": "https:\/\/movie.douban.com\/subject\/30241298\/",
        "playable": false,
        "cover": "https://img2.doubanio.com\/view\/photo\/s_ratio_poster\/public\/p2581888792.jpg",
        "id": "30241298",
        "cover_y": 1361,
        "is_new": false
    }, {
        "rate": "6.7",
        "cover_x": 2757,
        "title": "逃跑",
        "url": "https:\/\/movie.douban.com\/subject\/30243396\/",
        "playable": false,
        "cover": "https://img2.doubanio.com\/view\/photo\/s_ratio_poster\/public\/p2587085523.jpg",
        "id": "30243396",
        "cover_y": 4096,
        "is_new": false
    }, {
        "rate": "7.8",
        "cover_x": 1403,
        "title": "担保",
        "url": "https:\/\/movie.douban.com\/subject\/30475125\/",
        "playable": false,
        "cover": "https://img9.doubanio.com\/view\/photo\/s_ratio_poster\/public\/p2616180034.jpg",
        "id": "30475125",
        "cover_y": 2000,
        "is_new": false
    }, {
        "rate": "6.7",
        "cover_x": 1134,
        "title": "一点就到家",
        "url": "https:\/\/movie.douban.com\/subject\/35069506\/",
        "playable": true,
        "cover": "https://img2.doubanio.com\/view\/photo\/s_ratio_poster\/public\/p2621101922.jpg",
        "id": "35069506",
        "cover_y": 1588,
        "is_new": false
    }, {
        "rate": "8.2",
        "cover_x": 1456,
        "title": "鸣鸟不飞：乌云密布",
        "url": "https:\/\/movie.douban.com\/subject\/33425932\/",
        "playable": false,
        "cover": "https://img9.doubanio.com\/view\/photo\/s_ratio_poster\/public\/p2586787185.jpg",
        "id": "33425932",
        "cover_y": 2048,
        "is_new": false
    }, {
        "rate": "6.3",
        "cover_x": 1500,
        "title": "毕业舞会",
        "url": "https:\/\/movie.douban.com\/subject\/33422501\/",
        "playable": false,
        "cover": "https://img1.doubanio.com\/view\/photo\/s_ratio_poster\/public\/p2627517148.jpg",
        "id": "33422501",
        "cover_y": 2222,
        "is_new": false
    }, {
        "rate": "5.8",
        "cover_x": 2764,
        "title": "女巫",
        "url": "https:\/\/movie.douban.com\/subject\/3346423\/",
        "playable": false,
        "cover": "https://img3.doubanio.com\/view\/photo\/s_ratio_poster\/public\/p2621884130.jpg",
        "id": "3346423",
        "cover_y": 4096,
        "is_new": false
    }, {
        "rate": "7.2",
        "cover_x": 4000,
        "title": "隐形人",
        "url": "https:\/\/movie.douban.com\/subject\/2364086\/",
        "playable": false,
        "cover": "https://img9.doubanio.com\/view\/photo\/s_ratio_poster\/public\/p2624945594.jpg",
        "id": "2364086",
        "cover_y": 5936,
        "is_new": false
    }, {
        "rate": "7.4",
        "cover_x": 2121,
        "title": "温蒂妮",
        "url": "https:\/\/movie.douban.com\/subject\/34603816\/",
        "playable": true,
        "cover": "https://img2.doubanio.com\/view\/photo\/s_ratio_poster\/public\/p2599824382.jpg",
        "id": "34603816",
        "cover_y": 3000,
        "is_new": false
    }, {
        "rate": "6.8",
        "cover_x": 1500,
        "title": "蓝调天后",
        "url": "https:\/\/movie.douban.com\/subject\/34439631\/",
        "playable": false,
        "cover": "https://img1.doubanio.com\/view\/photo\/s_ratio_poster\/public\/p2623338779.jpg",
        "id": "34439631",
        "cover_y": 2222,
        "is_new": false
    }, {
        "rate": "5.5",
        "cover_x": 1080,
        "title": "我在时间尽头等你",
        "url": "https:\/\/movie.douban.com\/subject\/26661193\/",
        "playable": true,
        "cover": "https://img3.doubanio.com\/view\/photo\/s_ratio_poster\/public\/p2614225081.jpg",
        "id": "26661193",
        "cover_y": 1512,
        "is_new": false
    }, {
        "rate": "6.5",
        "cover_x": 1382,
        "title": "让他们说吧",
        "url": "https:\/\/movie.douban.com\/subject\/34797673\/",
        "playable": false,
        "cover": "https://img9.doubanio.com\/view\/photo\/s_ratio_poster\/public\/p2625712624.jpg",
        "id": "34797673",
        "cover_y": 2047,
        "is_new": true
    }, {
        "rate": "8.5",
        "cover_x": 1063,
        "title": "进击的巨人：编年史",
        "url": "https:\/\/movie.douban.com\/subject\/35088569\/",
        "playable": false,
        "cover": "https://img1.doubanio.com\/view\/photo\/s_ratio_poster\/public\/p2606366038.jpg",
        "id": "35088569",
        "cover_y": 1500,
        "is_new": false
    }]
}